<?xml version="1.0" encoding="UTF-8" ?>
<MResourcePanel id="bd.element.manager">
  <panel layout="BorderLayout">
  	<panel layout="FlowLayout(FlowLayout.RIGHT)" constraints="BorderLayout.NORTH">
  		<button id="settingButton" Text="设置" actionId="func.setting">
  		</button>
  	</panel>
  	<panel layout="BorderLayout" constraints="BorderLayout.CENTER">
  		<scrollpane constraints="BorderLayout.CENTER">
  			<table id="bdElementTable">
  				<BDElementTableModel sqlid="getAllBDElementTableMeta" params="" lazy="false"
  					columns="code,代码;name,名称;physical_table,物理表名;is_used,是否启用,java.lang.Boolean;">
  				</BDElementTableModel>
  			</table>
  		</scrollpane>
  	</panel>     
  </panel>
</MResourcePanel> 